ofxstatement_mastercard_de-0.1.0-py3.10-nspkg.pth
ofxstatement/plugins/mastercard_de.py
ofxstatement_mastercard_de-0.1.0.dist-info/LICENSE
ofxstatement_mastercard_de-0.1.0.dist-info/METADATA
ofxstatement_mastercard_de-0.1.0.dist-info/WHEEL
ofxstatement_mastercard_de-0.1.0.dist-info/entry_points.txt
ofxstatement_mastercard_de-0.1.0.dist-info/namespace_packages.txt
ofxstatement_mastercard_de-0.1.0.dist-info/top_level.txt
ofxstatement_mastercard_de-0.1.0.dist-info/zip-safe
ofxstatement_mastercard_de-0.1.0.dist-info/RECORD
