Metadata-Version: 2.1
Name: ofxstatement-mastercard-de
Version: 0.1.0
Summary: OFXStatement plugin for Mastercard statements (Germany)
Home-page: https://github.com/FliegendeWurst/ofxstatement-mastercard-de
Author: Arne Keller
Author-email: arne.keller@posteo.de
License: GPLv3
Keywords: ofx,banking,statement
Classifier: Development Status :: 3 - Alpha
Classifier: Programming Language :: Python :: 3
Classifier: Natural Language :: English
Classifier: Topic :: Office/Business :: Financial :: Accounting
Classifier: Topic :: Utilities
Classifier: Environment :: Console
Classifier: Operating System :: OS Independent
Classifier: License :: OSI Approved :: GNU General Public License v3 (GPLv3)
Classifier: Intended Audience :: End Users/Desktop
License-File: LICENSE
Requires-Dist: ofxstatement
